{
  "workout": {
    "date": "2026-05-26",
    "day_label": "Tuesday, May 26",
    "session_type": "Lower Body",
    "is_gym_day": true,
    "warmup": "Incline walk · 8-10 min · 3.3-3.5 mph · 6-8% incline",
    "finisher": "Incline walk · 10 min · 3.4 mph · 6-8% incline (skip if session hits 65 min)",
    "exercises": [
      {
        "id": "A",
        "name": "Leg Press",
        "detail": "360 lb × 10 · 3 sets",
        "rest": "90s rest",
        "note": "Clean 3×10 at 355 last Friday. Controlled tempo, don't lock knees at top."
      },
      {
        "id": "B",
        "name": "Hip Thrust Machine",
        "detail": "165 lb × 12 · 3 sets",
        "rest": "75s rest",
        "note": "Hit 160 cleanly last Friday. Full hip extension, squeeze at top, no hyperextension."
      },
      {
        "id": "C",
        "name": "DB Romanian Deadlift",
        "detail": "50 lb × 12 · 3 sets",
        "rest": "75s rest",
        "note": "Hit 45×12×3 last week. Hinge from hips, soft knee bend, back stays flat."
      },
      {
        "id": "D",
        "name": "Leg Curl",
        "detail": "77 lb × 12 · 3 sets",
        "rest": "75s rest",
        "note": "88 was too much last Friday — got 10/9 then dropped. Back to 77, push for 12 each set."
      },
      {
        "id": "E",
        "name": "KB Swing (Two-Hand)",
        "detail": "35 lb × 15 · 3 sets",
        "rest": "60s rest",
        "note": "30 felt light in early May — time to try 35. Drive with hips, not arms."
      },
      {
        "id": "F",
        "name": "Core Circuit C",
        "detail": "Cable Crunch 50 lb × 12 + Hanging Knee Raise × 10-12 + Side Plank 25s/side · 2 rounds",
        "rest": "60s between rounds",
        "note": "Haven't hit this combo recently. Kneeling cable crunch — round into it. Full hang on knee raise."
      }
    ]
  },
  "week": [
    {
      "date": "2026-05-25",
      "day_short": "Mon May 25",
      "session_type": "Upper Body ✓",
      "type": "gym",
      "note": "Done — incline bench 10/10/8, shoulder press 3×10 (12 on set 3), T-bar row 3×10 (12 on set 3)"
    },
    {
      "date": "2026-05-26",
      "day_short": "Tue May 26",
      "session_type": "Lower Body",
      "type": "gym",
      "note": "Leg press 360 · hip thrust 165 · RDL 50 · leg curl 77×12 · KB swing 35 · core circuit C"
    },
    {
      "date": "2026-05-27",
      "day_short": "Wed May 27",
      "session_type": "Rest Day",
      "type": "rest",
      "note": "Full rest · stay on nutrition"
    },
    {
      "date": "2026-05-28",
      "day_short": "Thu May 28",
      "session_type": "Upper Body",
      "type": "gym",
      "note": "Upper body — plan coming Thursday"
    },
    {
      "date": "2026-05-29",
      "day_short": "Fri May 29",
      "session_type": "Lower Body",
      "type": "gym",
      "note": "Lower body — plan coming Friday"
    },
    {
      "date": "2026-05-30",
      "day_short": "Sat May 30",
      "session_type": "Flexible",
      "type": "cardio",
      "note": "HIIT class, pickleball, or rest"
    },
    {
      "date": "2026-05-31",
      "day_short": "Sun May 31",
      "session_type": "Rest / Active",
      "type": "rest",
      "note": "Rest or light active recovery"
    }
  ]
}